pyctb/__init__.py
pyctb/register.py
pyctb/rfuncs.py
pyctb/version.py
pyctb-0.0.6.dist-info/LICENSE.txt
pyctb-0.0.6.dist-info/METADATA
pyctb-0.0.6.dist-info/WHEEL
pyctb-0.0.6.dist-info/top_level.txt
pyctb-0.0.6.dist-info/RECORD
