Metadata-Version: 2.1
Name: pyctb
Version: 0.0.6
Summary: Python Customized Tracebacks
Home-page: https://github.com/hrbigelow/pyctb
Author: Henry Bigelow
Author-email: hrbigelow@gmail.com
License: MIT
License-File: LICENSE.txt
Requires-Dist: stack-data (>=0.6.1)
